MANIFEST.in
README.rst
setup.py
unittest_utils/__init__.py
unittest_utils/case.py
unittest_utils/loader.py
unittest_utils/main.py
unittest_utils/result.py
unittest_utils/runner.py
unittest_utils.egg-info/PKG-INFO
unittest_utils.egg-info/SOURCES.txt
unittest_utils.egg-info/dependency_links.txt
unittest_utils.egg-info/entry_points.txt
unittest_utils.egg-info/not-zip-safe
unittest_utils.egg-info/requires.txt
unittest_utils.egg-info/top_level.txt