Metadata-Version: 1.0
Name: unittest-utils
Version: 0.1.2
Summary: Some custom utils for unittest2
Home-page: UNKNOWN
Author: UNKNOWN
Author-email: UNKNOWN
License: UNKNOWN
Platform: UNKNOWN
